factories/__init__.py
factories/constants.py
factories/factory.py
factories/examples/__init__.py
factories/examples/reader/__init__.py
factories/examples/reader/core.py
factories/examples/zoo/__init__.py
factories/examples/zoo/zoo.py
factories/tests/__init__.py
factories/tests/test_factory.py
factories/tests/alternate_plugins/__init__.py
factories/tests/alternate_plugins/other_animals.py
factories/tests/test_plugins/__init__.py
factories/tests/test_plugins/additional_reader.py
factories/tests/test_plugins/new_animals.py
factories/tests/test_plugins/uninspectable.py
factories/tests/test_plugins/unloadable.py
factories/tests/test_plugins/versioned_readers.py
factories-1.4.1.dist-info/LICENSE
factories-1.4.1.dist-info/METADATA
factories-1.4.1.dist-info/WHEEL
factories-1.4.1.dist-info/top_level.txt
factories-1.4.1.dist-info/RECORD
