Metadata-Version: 2.2
Name: factories
Version: 1.4.1
Summary: A python package exposing the factory/plugin design pattern
Home-page: https://github.com/mikemalinowski/factories
Author: Mike Malinowski
Author-email: mike.malinowski@outlook.com
Classifier: Programming Language :: Python
Classifier: License :: OSI Approved :: MIT License
Classifier: Operating System :: OS Independent
Requires-Python: >3.1.1
License-File: LICENSE
Requires-Dist: signalling
Dynamic: author
Dynamic: author-email
Dynamic: classifier
Dynamic: description
Dynamic: description-content-type
Dynamic: home-page
Dynamic: requires-dist
Dynamic: requires-python
Dynamic: summary
